fdserver/__init__.py
fdserver/__main__.py
fdserver/data/k6gte-fdserver-128.png
fdserver/data/k6gte-fdserver-32.png
fdserver/data/k6gte-fdserver-64.png
fdserver/data/k6gte-fdserver.desktop
fdserver/data/k6gte.fdserver.svg
fdserver/data/server_preferences.json
fdserver/lib/__init__.py
fdserver/lib/server_database.py
fdserver/lib/version.py
fdserver/lib/versiontest.py
fdserver-25.7.12.1.dist-info/licenses/LICENSE.md
fdserver-25.7.12.1.dist-info/METADATA
fdserver-25.7.12.1.dist-info/WHEEL
fdserver-25.7.12.1.dist-info/entry_points.txt
fdserver-25.7.12.1.dist-info/top_level.txt
fdserver-25.7.12.1.dist-info/RECORD
